{
    "keep": {
        "days": false,
        "amount": 30
    },
    "auditLog": "logs/error/.5f1151ced196762ae8720e2c85f1519895bd259e-audit.json",
    "files": [
        {
            "date": 1633337885030,
            "name": "logs/error/2021-10-04.error.log",
            "hash": "d765a193d57d626b1fbe6e21d0a25b47"
        },
        {
            "date": 1633364763305,
            "name": "logs/error/2021-10-05.error.log",
            "hash": "bd2c6dfacbac535dd0bba4fafe61c2da"
        },
        {
            "date": 1633483025140,
            "name": "logs/error/2021-10-06.error.log",
            "hash": "935227ae2025c5267d01faf0f0943d3f"
        },
        {
            "date": 1633458901258,
            "name": "logs/error/2021-10-06.error.log",
            "hash": "2d8b3c8c3c4330a4d0edef23240e4cde"
        },
        {
            "date": 1633673411980,
            "name": "logs/error/2021-10-08.error.log",
            "hash": "1e02c0d87e22f0943babc992fa16e50e"
        },
        {
            "date": 1633747349486,
            "name": "logs/error/2021-10-09.error.log",
            "hash": "8aebaf727bde581c587268ccaeb3d31f"
        },
        {
            "date": 1633916937310,
            "name": "logs/error/2021-10-11.error.log",
            "hash": "a7909d00ee73accad3f20f87592f2e53"
        }
    ]
}